sanic_sa_datatable/__init__.py
Sanic_Sqlalchemy_DataTable-0.0.8.dist-info/LICENSE
Sanic_Sqlalchemy_DataTable-0.0.8.dist-info/METADATA
Sanic_Sqlalchemy_DataTable-0.0.8.dist-info/WHEEL
Sanic_Sqlalchemy_DataTable-0.0.8.dist-info/top_level.txt
Sanic_Sqlalchemy_DataTable-0.0.8.dist-info/RECORD
