Metadata-Version: 2.1
Name: Sanic-Sqlalchemy-DataTable
Version: 0.0.8
Summary: datatable backend.
Home-page: https://github.com/htwenning/datatable
Author: wenning
Author-email: ht.wenning@foxmail.com
License: MIT
Platform: any
Requires-Dist: SQLAlchemy (==1.2.17)
Requires-Dist: sanic (==18.12.0)
